{
  "version": "7",
  "dialect": "postgresql",
  "entries": [
    {
      "idx": 0,
      "version": "7",
      "when": 1756119888667,
      "tag": "0000_rapid_mojo",
      "breakpoints": true
    },
    {
      "idx": 1,
      "version": "7",
      "when": 1756130799896,
      "tag": "0001_silky_gorgon",
      "breakpoints": true
    },
    {
      "idx": 2,
      "version": "7",
      "when": 1756143278811,
      "tag": "0002_salty_payback",
      "breakpoints": true
    },
    {
      "idx": 3,
      "version": "7",
      "when": 1756183963309,
      "tag": "0003_lush_mister_fear",
      "breakpoints": true
    }
  ]
}